{
  "ceny": [
    {
      "nazwa": "Traficar kilometrowy",
      "Operator": "Traficar",
      "Grupa": "Traficar",
      "start": 3.99,
      "km": 1.79,
      "km_free": 0,
      "minuty_free": 0,
      "min_jazdy": 0,
      "min_postoj": 0.15,
      "miasta": [
        "Kraków",
        "Warszawa",
        "Wrocław",
        "Poznań",
        "Trójmiasto",
        "Łódź",
        "Chorzów",
        "Katowice",
        "Siemianowice Śląskie",
        "Sosnowiec",
        "Świętochłowice",
        "Szczecin"
      ]
    },
    {
      "nazwa": "Traficar dobowy duże miejskie",
      "Operator": "Traficar",
      "Grupa": "Duże",
      "start": 99,
      "km": 0.99,
      "km_free": 0,
      "minuty_free": 0,
      "min_jazdy": 0,
      "min_postoj": 0,
      "miasta": [
        "Kraków",
        "Warszawa",
        "Wrocław",
        "Poznań",
        "Trójmiasto",
        "Łódź",
        "Chorzów",
        "Katowice",
        "Siemianowice Śląskie",
        "Sosnowiec",
        "Świętochłowice",
        "Szczecin"
      ]
    },
    {
      "nazwa": "Traficar kilometrowy duże miejskie",
      "Operator": "Traficar",
      "Grupa": "Duże",
      "start": 3.99,
      "km": 2.19,
      "km_free": 0,
      "minuty_free": 0,
      "min_jazdy": 0,
      "min_postoj": 0.15,
      "miasta": [
        "Kraków",
        "Warszawa",
        "Wrocław",
        "Poznań",
        "Trójmiasto",
        "Łódź",
        "Chorzów",
        "Katowice",
        "Siemianowice Śląskie",
        "Sosnowiec",
        "Świętochłowice",
        "Szczecin"
      ]
    },
    {
      "nazwa": "Traficar dobowy",
      "Operator": "Traficar",
      "Grupa": "Traficar",
      "start": 69,
      "km": 0.99,
      "km_free": 0,
      "minuty_free": 0,
      "min_jazdy": 0,
      "min_postoj": 0,
      "miasta": [
        "Kraków",
        "Warszawa",
        "Wrocław",
        "Poznań",
        "Trójmiasto",
        "Łódź",
        "Chorzów",
        "Katowice",
        "Siemianowice Śląskie",
        "Sosnowiec",
        "Świętochłowice",
        "Szczecin"
      ]
    },
    {
      "nazwa": "Panek osobowy",
      "Operator": "Panek",
      "Grupa": "OSOBOWE",
      "start": 5.99,
      "km_widelki": [
        {
          "od": 0,
          "do": 100,
          "cena_za_km": 2.19
        },
        {
          "od": 101,
          "do": 100000,
          "cena_za_km": 0.99
        }
      ],
      "km": 2.19,
      "km_free": 0,
      "min_jazdy": 0,
      "minuty_free": 0,
      "min_postoj": 0.19,
      "min_postoj_max_kwota_dobowa":99,
      "miasta": [
        "Białystok",
        "Bielsko-Biała",
        "Bydgoszcz",
        "Katowice",
        "Kraków",
        "Lublin",
        "Łódź",
        "Małe Trójmiasto",
        "Modlin Lotnisko",
        "Poznań",
        "Pyrzowice",
        "Rzeszów",
        "Szczecin",
        "Toruń",
        "Trójmiasto",
        "Warszawa",
        "Wrocław"
      ]
    },
    {
      "status" : "off",
      "nazwa": "Panek osobowy pseudodobowy",
      "Operator": "Panek",
      "Grupa": "OSOBOWE",
      "start": 99,
      "km": 0.99,
      "km_free": 0,
      "min_jazdy": 0,
      "minuty_free": 0,
      "min_postoj": 0,
      "miasta": [
        "Białystok",
        "Bielsko-Biała",
        "Bydgoszcz",
        "Katowice",
        "Kraków",
        "Lublin",
        "Łódź",
        "Małe Trójmiasto",
        "Modlin Lotnisko",
        "Poznań",
        "Pyrzowice",
        "Rzeszów",
        "Szczecin",
        "Toruń",
        "Trójmiasto",
        "Warszawa",
        "Wrocław"
      ]
    },
    {
      "nazwa": "4Mobility standardowy",
      "Operator": "4Mobility",
      "Grupa": "4Mobility",
      "start": 0,
      "km": 1.05,
      "km_free": 0,
      "minuty_free": 0,
      "min_jazdy": 1.1,
      "min_postoj": 0.2,
      "miasta": [
        "Warszawa",
        "Poznań",
        "Rzeszów",
        "Trójmiasto",
        "Wrocław",
        "Kraków"
      ]
    },
    {
      "nazwa": "4Mobility dobowy oklejony",
      "Operator": "4Mobility",
      "Grupa": "4Mobility",
      "start": 189,
      "km": 0.95,
      "km_free": 50,
      "minuty_free": 1440,
      "min_jazdy": 1.1,
      "min_postoj": 0.2,
      "miasta": [
        "Warszawa",
        "Poznań",
        "Rzeszów",
        "Trójmiasto",
        "Wrocław",
        "Kraków"
      ]
    }
  ]
}